colormapize/__init__.py
colormapize/core.py
colormapize-0.2.dist-info/LICENSE
colormapize-0.2.dist-info/METADATA
colormapize-0.2.dist-info/WHEEL
colormapize-0.2.dist-info/entry_points.txt
colormapize-0.2.dist-info/top_level.txt
colormapize-0.2.dist-info/zip-safe
colormapize-0.2.dist-info/RECORD
