Metadata-Version: 2.1
Name: colormapize
Version: 0.2
Summary: Generate a colormap from an image
Home-page: https://github.com/astrofrog/colormapize
Author: Thomas Robitaille
Author-email: thomas.robitaille@gmail.com
License: UNKNOWN
Platform: UNKNOWN
Requires-Dist: click
Requires-Dist: matplotlib
Requires-Dist: pillow
